{
  "runId": "2026-03-20_a1b2c3d",
  "prNumber": 3,
  "commitSha": "a1b2c3d4e5f6789012345678901234567890abcd",
  "createdAt": "2026-03-20T14:00:00.000Z",
  "tests": [
    {
      "name": "tests/app.test.ts auth > should login successfully",
      "durationMs": 2,
      "status": "passed",
      "wasFlaky": false
    },
    {
      "name": "tests/app.test.ts payments > should charge card",
      "durationMs": 1498,
      "status": "passed",
      "wasFlaky": false
    },
    {
      "name": "tests/app.test.ts profile > should load user data",
      "durationMs": 8,
      "status": "passed",
      "wasFlaky": true
    },
    {
      "name": "tests/app.test.ts notifications > should send email",
      "durationMs": 1,
      "status": "passed",
      "wasFlaky": false
    },
    {
      "name": "tests/app.test.ts settings > should save preferences",
      "durationMs": 3,
      "status": "passed",
      "wasFlaky": false
    }
  ]
}
