{
  "runId": "08b2e13-1774945846818",
  "prNumber": 0,
  "commitSha": "08b2e13d3a76e798e816175d04269afbad47da7d",
  "createdAt": "2026-03-31T08:30:46.818Z",
  "tests": [
    {
      "name": "example.spec.ts > auth > should login successfully",
      "durationMs": 2,
      "status": "passed",
      "wasFlaky": false
    },
    {
      "name": "example.spec.ts > auth > should logout successfully",
      "durationMs": 1,
      "status": "passed",
      "wasFlaky": false
    },
    {
      "name": "example.spec.ts > payments > should process payment",
      "durationMs": 1502,
      "status": "passed",
      "wasFlaky": false
    },
    {
      "name": "example.spec.ts > payments > should refund payment",
      "durationMs": 502,
      "status": "passed",
      "wasFlaky": false
    },
    {
      "name": "example.spec.ts > profile > should load user data",
      "durationMs": 1,
      "status": "passed",
      "wasFlaky": false
    },
    {
      "name": "example.spec.ts > profile > should update profile",
      "durationMs": 0,
      "status": "passed",
      "wasFlaky": false
    },
    {
      "name": "example.spec.ts > notifications > should send email notification",
      "durationMs": 0,
      "status": "passed",
      "wasFlaky": false
    },
    {
      "name": "example.spec.ts > notifications > should send push notification",
      "durationMs": 0,
      "status": "passed",
      "wasFlaky": false
    }
  ]
}